MANIFEST.in
requirements.txt
setup.cfg
setup.py
googlesheet/__init__.py
googlesheet/api.py
googlesheet/exceptions.py
googlesheet_python_sdk.egg-info/PKG-INFO
googlesheet_python_sdk.egg-info/SOURCES.txt
googlesheet_python_sdk.egg-info/dependency_links.txt
googlesheet_python_sdk.egg-info/requires.txt
googlesheet_python_sdk.egg-info/top_level.txt