Metadata-Version: 1.1
Name: googlesheet-python-sdk
Version: 1.0.0
Summary: Google Sheet API python client
Home-page: https://github.com/rohitkhatri/googlesheet-python-sdk
Author: Rohit Khatri
Author-email: developer.rohitkhatri@gmail.com
License: MIT
Keywords: googlesheet data api python v4
Platform: UNKNOWN
Classifier: Development Status :: 4 - Beta
Classifier: Intended Audience :: Developers
Classifier: Operating System :: OS Independent
Classifier: Programming Language :: Python :: 3.5
Classifier: Operating System :: OS Independent
Classifier: Topic :: Software Development :: Libraries :: Python Modules
